{
  "annotations": {
    "NS2": {
      "end": 330,
      "seqid": "config/reference_oc43_NS2.gb",
      "start": 1,
      "strand": "+",
      "type": "CDS"
    },
    "nuc": {
      "end": 330,
      "seqid": "config/reference_oc43_NS2.gb",
      "start": 1,
      "strand": "+",
      "type": "source"
    }
  },
  "generated_by": {
    "program": "augur",
    "version": "14.1.0"
  },
  "nodes": {
    "JN129834": {
      "aa_muts": {
        "NS2": []
      }
    },
    "JN129835": {
      "aa_muts": {
        "NS2": []
      }
    },
    "KF530059": {
      "aa_muts": {
        "NS2": []
      }
    },
    "KF530060": {
      "aa_muts": {
        "NS2": []
      }
    },
    "KF530061": {
      "aa_muts": {
        "NS2": []
      }
    },
    "KF530062": {
      "aa_muts": {
        "NS2": []
      }
    },
    "KF530063": {
      "aa_muts": {
        "NS2": []
      }
    },
    "KF530064": {
      "aa_muts": {
        "NS2": []
      }
    },
    "KF530065": {
      "aa_muts": {
        "NS2": []
      }
    },
    "KF530066": {
      "aa_muts": {
        "NS2": []
      }
    },
    "KF530067": {
      "aa_muts": {
        "NS2": []
      }
    },
    "KF530068": {
      "aa_muts": {
        "NS2": []
      }
    },
    "KF530069": {
      "aa_muts": {
        "NS2": []
      }
    },
    "KF530070": {
      "aa_muts": {
        "NS2": []
      }
    },
    "KF530071": {
      "aa_muts": {
        "NS2": []
      }
    },
    "KF530072": {
      "aa_muts": {
        "NS2": []
      }
    },
    "KF530073": {
      "aa_muts": {
        "NS2": []
      }
    },
    "KF530074": {
      "aa_muts": {
        "NS2": []
      }
    },
    "KF530075": {
      "aa_muts": {
        "NS2": []
      }
    },
    "KF530076": {
      "aa_muts": {
        "NS2": []
      }
    },
    "KF530077": {
      "aa_muts": {
        "NS2": []
      }
    },
    "KF530078": {
      "aa_muts": {
        "NS2": []
      }
    },
    "KF530079": {
      "aa_muts": {
        "NS2": []
      }
    },
    "KF530080": {
      "aa_muts": {
        "NS2": []
      }
    },
    "KF530081": {
      "aa_muts": {
        "NS2": []
      }
    },
    "KF530082": {
      "aa_muts": {
        "NS2": []
      }
    },
    "KF530083": {
      "aa_muts": {
        "NS2": []
      }
    },
    "KF530084": {
      "aa_muts": {
        "NS2": []
      }
    },
    "KF530085": {
      "aa_muts": {
        "NS2": [
          "I14T"
        ]
      }
    },
    "KF530086": {
      "aa_muts": {
        "NS2": []
      }
    },
    "KF530087": {
      "aa_muts": {
        "NS2": []
      }
    },
    "KF530088": {
      "aa_muts": {
        "NS2": []
      }
    },
    "KF530089": {
      "aa_muts": {
        "NS2": []
      }
    },
    "KF530090": {
      "aa_muts": {
        "NS2": []
      }
    },
    "KF530091": {
      "aa_muts": {
        "NS2": []
      }
    },
    "KF530092": {
      "aa_muts": {
        "NS2": []
      }
    },
    "KF530093": {
      "aa_muts": {
        "NS2": []
      }
    },
    "KF530094": {
      "aa_muts": {
        "NS2": []
      }
    },
    "KF530095": {
      "aa_muts": {
        "NS2": []
      }
    },
    "KF530096": {
      "aa_muts": {
        "NS2": []
      }
    },
    "KF530097": {
      "aa_muts": {
        "NS2": []
      }
    },
    "KF530098": {
      "aa_muts": {
        "NS2": []
      }
    },
    "KF530099": {
      "aa_muts": {
        "NS2": []
      }
    },
    "KF923886": {
      "aa_muts": {
        "NS2": []
      }
    },
    "KF923887": {
      "aa_muts": {
        "NS2": []
      }
    },
    "KF923888": {
      "aa_muts": {
        "NS2": []
      }
    },
    "KF923889": {
      "aa_muts": {
        "NS2": []
      }
    },
    "KF923890": {
      "aa_muts": {
        "NS2": []
      }
    },
    "KF923891": {
      "aa_muts": {
        "NS2": []
      }
    },
    "KF923892": {
      "aa_muts": {
        "NS2": []
      }
    },
    "KF923893": {
      "aa_muts": {
        "NS2": []
      }
    },
    "KF923894": {
      "aa_muts": {
        "NS2": []
      }
    },
    "KF923895": {
      "aa_muts": {
        "NS2": []
      }
    },
    "KF923896": {
      "aa_muts": {
        "NS2": []
      }
    },
    "KF923897": {
      "aa_muts": {
        "NS2": []
      }
    },
    "KF923898": {
      "aa_muts": {
        "NS2": []
      }
    },
    "KF923899": {
      "aa_muts": {
        "NS2": []
      }
    },
    "KF923900": {
      "aa_muts": {
        "NS2": []
      }
    },
    "KF923901": {
      "aa_muts": {
        "NS2": []
      }
    },
    "KF923902": {
      "aa_muts": {
        "NS2": []
      }
    },
    "KF923903": {
      "aa_muts": {
        "NS2": []
      }
    },
    "KF923904": {
      "aa_muts": {
        "NS2": []
      }
    },
    "KF923905": {
      "aa_muts": {
        "NS2": []
      }
    },
    "KF923906": {
      "aa_muts": {
        "NS2": []
      }
    },
    "KF923907": {
      "aa_muts": {
        "NS2": []
      }
    },
    "KF923908": {
      "aa_muts": {
        "NS2": []
      }
    },
    "KF923909": {
      "aa_muts": {
        "NS2": []
      }
    },
    "KF923910": {
      "aa_muts": {
        "NS2": []
      }
    },
    "KF923911": {
      "aa_muts": {
        "NS2": []
      }
    },
    "KF923912": {
      "aa_muts": {
        "NS2": []
      }
    },
    "KF923913": {
      "aa_muts": {
        "NS2": []
      }
    },
    "KF923914": {
      "aa_muts": {
        "NS2": []
      }
    },
    "KF923915": {
      "aa_muts": {
        "NS2": []
      }
    },
    "KF923916": {
      "aa_muts": {
        "NS2": []
      }
    },
    "KF923917": {
      "aa_muts": {
        "NS2": []
      }
    },
    "KF923918": {
      "aa_muts": {
        "NS2": []
      }
    },
    "KF923919": {
      "aa_muts": {
        "NS2": []
      }
    },
    "KF923920": {
      "aa_muts": {
        "NS2": []
      }
    },
    "KF923921": {
      "aa_muts": {
        "NS2": [
          "L11P",
          "R12P"
        ]
      }
    },
    "KF923922": {
      "aa_muts": {
        "NS2": []
      }
    },
    "KF923923": {
      "aa_muts": {
        "NS2": []
      }
    },
    "KF923924": {
      "aa_muts": {
        "NS2": []
      }
    },
    "KF923925": {
      "aa_muts": {
        "NS2": []
      }
    },
    "KJ958218": {
      "aa_muts": {
        "NS2": []
      }
    },
    "KJ958219": {
      "aa_muts": {
        "NS2": []
      }
    },
    "KP198610": {
      "aa_muts": {
        "NS2": []
      }
    },
    "KP198611": {
      "aa_muts": {
        "NS2": []
      }
    },
    "KU131570": {
      "aa_muts": {
        "NS2": []
      }
    },
    "KX344031": {
      "aa_muts": {
        "NS2": []
      }
    },
    "KX538964": {
      "aa_muts": {
        "NS2": []
      }
    },
    "KX538965": {
      "aa_muts": {
        "NS2": [
          "N18K"
        ]
      }
    },
    "KX538966": {
      "aa_muts": {
        "NS2": []
      }
    },
    "KX538967": {
      "aa_muts": {
        "NS2": []
      }
    },
    "KX538968": {
      "aa_muts": {
        "NS2": []
      }
    },
    "KX538969": {
      "aa_muts": {
        "NS2": []
      }
    },
    "KX538970": {
      "aa_muts": {
        "NS2": []
      }
    },
    "KX538971": {
      "aa_muts": {
        "NS2": []
      }
    },
    "KX538972": {
      "aa_muts": {
        "NS2": []
      }
    },
    "KX538973": {
      "aa_muts": {
        "NS2": []
      }
    },
    "KX538974": {
      "aa_muts": {
        "NS2": []
      }
    },
    "KX538975": {
      "aa_muts": {
        "NS2": []
      }
    },
    "KX538976": {
      "aa_muts": {
        "NS2": []
      }
    },
    "KX538977": {
      "aa_muts": {
        "NS2": []
      }
    },
    "KX538978": {
      "aa_muts": {
        "NS2": []
      }
    },
    "KX538979": {
      "aa_muts": {
        "NS2": []
      }
    },
    "KY014281": {
      "aa_muts": {
        "NS2": []
      }
    },
    "KY014282": {
      "aa_muts": {
        "NS2": []
      }
    },
    "KY369905": {
      "aa_muts": {
        "NS2": []
      }
    },
    "KY369906": {
      "aa_muts": {
        "NS2": []
      }
    },
    "KY369907": {
      "aa_muts": {
        "NS2": []
      }
    },
    "KY554972": {
      "aa_muts": {
        "NS2": []
      }
    },
    "KY554973": {
      "aa_muts": {
        "NS2": []
      }
    },
    "KY554974": {
      "aa_muts": {
        "NS2": []
      }
    },
    "KY554975": {
      "aa_muts": {
        "NS2": []
      }
    },
    "KY674917": {
      "aa_muts": {
        "NS2": []
      }
    },
    "KY674918": {
      "aa_muts": {
        "NS2": []
      }
    },
    "KY674920": {
      "aa_muts": {
        "NS2": []
      }
    },
    "KY684759": {
      "aa_muts": {
        "NS2": []
      }
    },
    "KY967356": {
      "aa_muts": {
        "NS2": []
      }
    },
    "KY967358": {
      "aa_muts": {
        "NS2": []
      }
    },
    "KY967359": {
      "aa_muts": {
        "NS2": []
      }
    },
    "KY967360": {
      "aa_muts": {
        "NS2": []
      }
    },
    "KY967361": {
      "aa_muts": {
        "NS2": []
      }
    },
    "KY983583": {
      "aa_muts": {
        "NS2": []
      }
    },
    "KY983585": {
      "aa_muts": {
        "NS2": []
      }
    },
    "KY983588": {
      "aa_muts": {
        "NS2": []
      }
    },
    "LC315646": {
      "aa_muts": {
        "NS2": []
      }
    },
    "LC315647": {
      "aa_muts": {
        "NS2": []
      }
    },
    "LC315648": {
      "aa_muts": {
        "NS2": []
      }
    },
    "LC315649": {
      "aa_muts": {
        "NS2": []
      }
    },
    "LC687398": {
      "aa_muts": {
        "NS2": []
      }
    },
    "LC687399": {
      "aa_muts": {
        "NS2": []
      }
    },
    "LC687400": {
      "aa_muts": {
        "NS2": []
      }
    },
    "LC720427": {
      "aa_muts": {
        "NS2": []
      }
    },
    "LC720429": {
      "aa_muts": {
        "NS2": []
      }
    },
    "MF314143": {
      "aa_muts": {
        "NS2": []
      }
    },
    "MF374983": {
      "aa_muts": {
        "NS2": []
      }
    },
    "MF374984": {
      "aa_muts": {
        "NS2": []
      }
    },
    "MF374985": {
      "aa_muts": {
        "NS2": []
      }
    },
    "MG977451": {
      "aa_muts": {
        "NS2": []
      }
    },
    "MG977452": {
      "aa_muts": {
        "NS2": []
      }
    },
    "MH121121": {
      "aa_muts": {
        "NS2": []
      }
    },
    "MH828490": {
      "aa_muts": {
        "NS2": []
      }
    },
    "MN026164": {
      "aa_muts": {
        "NS2": []
      }
    },
    "MN026165": {
      "aa_muts": {
        "NS2": []
      }
    },
    "MN306036": {
      "aa_muts": {
        "NS2": []
      }
    },
    "MN306041": {
      "aa_muts": {
        "NS2": []
      }
    },
    "MN306042": {
      "aa_muts": {
        "NS2": []
      }
    },
    "MN306043": {
      "aa_muts": {
        "NS2": []
      }
    },
    "MN306053": {
      "aa_muts": {
        "NS2": []
      }
    },
    "MN310476": {
      "aa_muts": {
        "NS2": []
      }
    },
    "MN310478": {
      "aa_muts": {
        "NS2": []
      }
    },
    "MT118667": {
      "aa_muts": {
        "NS2": []
      }
    },
    "MT118668": {
      "aa_muts": {
        "NS2": []
      }
    },
    "MT118671": {
      "aa_muts": {
        "NS2": []
      }
    },
    "MT118672": {
      "aa_muts": {
        "NS2": []
      }
    },
    "MT118673": {
      "aa_muts": {
        "NS2": []
      }
    },
    "MT118678": {
      "aa_muts": {
        "NS2": []
      }
    },
    "MT118683": {
      "aa_muts": {
        "NS2": []
      }
    },
    "MT118685": {
      "aa_muts": {
        "NS2": []
      }
    },
    "MT118692": {
      "aa_muts": {
        "NS2": []
      }
    },
    "MW052042": {
      "aa_muts": {
        "NS2": []
      }
    },
    "MW411432": {
      "aa_muts": {
        "NS2": []
      }
    },
    "MW411433": {
      "aa_muts": {
        "NS2": []
      }
    },
    "MW559057": {
      "aa_muts": {
        "NS2": []
      }
    },
    "MW587040": {
      "aa_muts": {
        "NS2": []
      }
    },
    "MW587041": {
      "aa_muts": {
        "NS2": []
      }
    },
    "MW587042": {
      "aa_muts": {
        "NS2": []
      }
    },
    "MW938760": {
      "aa_muts": {
        "NS2": [
          "T99N"
        ]
      }
    },
    "NODE_0000000": {
      "aa_muts": {},
      "aa_sequences": {
        "NS2": "MDIWRPEKKYLRYINGFNVSELEDACFKFNYQFPKVGYCRVPSHAWCRNQGRFCATFTLYGKSKHYDKYFGVINGFTAFANTVEDAVNKLVFLAVDFITWRRQELNVYG*"
      }
    },
    "NODE_0000002": {
      "aa_muts": {
        "NS2": []
      }
    },
    "NODE_0000003": {
      "aa_muts": {
        "NS2": []
      }
    },
    "NODE_0000004": {
      "aa_muts": {
        "NS2": []
      }
    },
    "NODE_0000005": {
      "aa_muts": {
        "NS2": []
      }
    },
    "NODE_0000006": {
      "aa_muts": {
        "NS2": []
      }
    },
    "NODE_0000007": {
      "aa_muts": {
        "NS2": []
      }
    },
    "NODE_0000008": {
      "aa_muts": {
        "NS2": []
      }
    },
    "NODE_0000009": {
      "aa_muts": {
        "NS2": []
      }
    },
    "NODE_0000010": {
      "aa_muts": {
        "NS2": []
      }
    },
    "NODE_0000011": {
      "aa_muts": {
        "NS2": []
      }
    },
    "NODE_0000012": {
      "aa_muts": {
        "NS2": [
          "Y10F"
        ]
      }
    },
    "NODE_0000013": {
      "aa_muts": {
        "NS2": []
      }
    },
    "NODE_0000014": {
      "aa_muts": {
        "NS2": [
          "K35R"
        ]
      }
    },
    "NODE_0000015": {
      "aa_muts": {
        "NS2": [
          "F10Y"
        ]
      }
    },
    "NODE_0000016": {
      "aa_muts": {
        "NS2": []
      }
    },
    "NODE_0000019": {
      "aa_muts": {
        "NS2": []
      }
    },
    "NODE_0000020": {
      "aa_muts": {
        "NS2": []
      }
    },
    "NODE_0000021": {
      "aa_muts": {
        "NS2": []
      }
    },
    "NODE_0000022": {
      "aa_muts": {
        "NS2": [
          "A78V"
        ]
      }
    },
    "NODE_0000023": {
      "aa_muts": {
        "NS2": []
      }
    },
    "NODE_0000024": {
      "aa_muts": {
        "NS2": []
      }
    },
    "NODE_0000025": {
      "aa_muts": {
        "NS2": []
      }
    },
    "NODE_0000026": {
      "aa_muts": {
        "NS2": []
      }
    },
    "NODE_0000027": {
      "aa_muts": {
        "NS2": []
      }
    },
    "NODE_0000028": {
      "aa_muts": {
        "NS2": []
      }
    },
    "NODE_0000030": {
      "aa_muts": {
        "NS2": []
      }
    },
    "NODE_0000031": {
      "aa_muts": {
        "NS2": []
      }
    },
    "NODE_0000032": {
      "aa_muts": {
        "NS2": []
      }
    },
    "NODE_0000033": {
      "aa_muts": {
        "NS2": []
      }
    },
    "NODE_0000034": {
      "aa_muts": {
        "NS2": []
      }
    },
    "NODE_0000038": {
      "aa_muts": {
        "NS2": []
      }
    },
    "NODE_0000039": {
      "aa_muts": {
        "NS2": []
      }
    },
    "NODE_0000040": {
      "aa_muts": {
        "NS2": []
      }
    },
    "NODE_0000041": {
      "aa_muts": {
        "NS2": []
      }
    },
    "NODE_0000045": {
      "aa_muts": {
        "NS2": []
      }
    },
    "NODE_0000046": {
      "aa_muts": {
        "NS2": []
      }
    },
    "NODE_0000047": {
      "aa_muts": {
        "NS2": []
      }
    },
    "NODE_0000048": {
      "aa_muts": {
        "NS2": []
      }
    },
    "NODE_0000049": {
      "aa_muts": {
        "NS2": []
      }
    },
    "NODE_0000050": {
      "aa_muts": {
        "NS2": []
      }
    },
    "NODE_0000051": {
      "aa_muts": {
        "NS2": []
      }
    },
    "NODE_0000052": {
      "aa_muts": {
        "NS2": []
      }
    },
    "NODE_0000053": {
      "aa_muts": {
        "NS2": []
      }
    },
    "NODE_0000054": {
      "aa_muts": {
        "NS2": []
      }
    },
    "NODE_0000055": {
      "aa_muts": {
        "NS2": []
      }
    },
    "NODE_0000056": {
      "aa_muts": {
        "NS2": []
      }
    },
    "NODE_0000057": {
      "aa_muts": {
        "NS2": []
      }
    },
    "NODE_0000058": {
      "aa_muts": {
        "NS2": []
      }
    },
    "NODE_0000059": {
      "aa_muts": {
        "NS2": []
      }
    },
    "NODE_0000060": {
      "aa_muts": {
        "NS2": []
      }
    },
    "NODE_0000061": {
      "aa_muts": {
        "NS2": []
      }
    },
    "NODE_0000062": {
      "aa_muts": {
        "NS2": []
      }
    },
    "NODE_0000063": {
      "aa_muts": {
        "NS2": []
      }
    },
    "NODE_0000064": {
      "aa_muts": {
        "NS2": []
      }
    },
    "NODE_0000065": {
      "aa_muts": {
        "NS2": []
      }
    },
    "NODE_0000066": {
      "aa_muts": {
        "NS2": []
      }
    },
    "NODE_0000067": {
      "aa_muts": {
        "NS2": []
      }
    },
    "NODE_0000068": {
      "aa_muts": {
        "NS2": []
      }
    },
    "NODE_0000069": {
      "aa_muts": {
        "NS2": []
      }
    },
    "NODE_0000070": {
      "aa_muts": {
        "NS2": []
      }
    },
    "NODE_0000071": {
      "aa_muts": {
        "NS2": []
      }
    },
    "NODE_0000072": {
      "aa_muts": {
        "NS2": []
      }
    },
    "NODE_0000073": {
      "aa_muts": {
        "NS2": []
      }
    },
    "NODE_0000074": {
      "aa_muts": {
        "NS2": []
      }
    },
    "NODE_0000075": {
      "aa_muts": {
        "NS2": []
      }
    },
    "NODE_0000076": {
      "aa_muts": {
        "NS2": []
      }
    },
    "NODE_0000077": {
      "aa_muts": {
        "NS2": []
      }
    },
    "NODE_0000078": {
      "aa_muts": {
        "NS2": []
      }
    },
    "NODE_0000079": {
      "aa_muts": {
        "NS2": []
      }
    },
    "NODE_0000080": {
      "aa_muts": {
        "NS2": []
      }
    },
    "NODE_0000081": {
      "aa_muts": {
        "NS2": []
      }
    },
    "NODE_0000082": {
      "aa_muts": {
        "NS2": []
      }
    },
    "NODE_0000083": {
      "aa_muts": {
        "NS2": []
      }
    },
    "NODE_0000084": {
      "aa_muts": {
        "NS2": []
      }
    },
    "NODE_0000085": {
      "aa_muts": {
        "NS2": []
      }
    },
    "NODE_0000086": {
      "aa_muts": {
        "NS2": []
      }
    },
    "NODE_0000087": {
      "aa_muts": {
        "NS2": []
      }
    },
    "NODE_0000088": {
      "aa_muts": {
        "NS2": []
      }
    },
    "NODE_0000089": {
      "aa_muts": {
        "NS2": []
      }
    },
    "NODE_0000090": {
      "aa_muts": {
        "NS2": []
      }
    },
    "NODE_0000091": {
      "aa_muts": {
        "NS2": []
      }
    },
    "NODE_0000092": {
      "aa_muts": {
        "NS2": []
      }
    },
    "NODE_0000093": {
      "aa_muts": {
        "NS2": []
      }
    },
    "NODE_0000094": {
      "aa_muts": {
        "NS2": []
      }
    },
    "NODE_0000095": {
      "aa_muts": {
        "NS2": []
      }
    },
    "NODE_0000096": {
      "aa_muts": {
        "NS2": []
      }
    },
    "NODE_0000097": {
      "aa_muts": {
        "NS2": []
      }
    },
    "NODE_0000098": {
      "aa_muts": {
        "NS2": []
      }
    },
    "NODE_0000099": {
      "aa_muts": {
        "NS2": []
      }
    },
    "NODE_0000100": {
      "aa_muts": {
        "NS2": []
      }
    },
    "NODE_0000101": {
      "aa_muts": {
        "NS2": []
      }
    },
    "NODE_0000102": {
      "aa_muts": {
        "NS2": [
          "F27S"
        ]
      }
    },
    "NODE_0000103": {
      "aa_muts": {
        "NS2": []
      }
    },
    "NODE_0000104": {
      "aa_muts": {
        "NS2": []
      }
    },
    "NODE_0000105": {
      "aa_muts": {
        "NS2": []
      }
    },
    "NODE_0000106": {
      "aa_muts": {
        "NS2": []
      }
    },
    "NODE_0000107": {
      "aa_muts": {
        "NS2": []
      }
    },
    "NODE_0000108": {
      "aa_muts": {
        "NS2": []
      }
    },
    "NODE_0000109": {
      "aa_muts": {
        "NS2": []
      }
    },
    "NODE_0000110": {
      "aa_muts": {
        "NS2": []
      }
    },
    "NODE_0000111": {
      "aa_muts": {
        "NS2": [
          "R52K"
        ]
      }
    },
    "NODE_0000112": {
      "aa_muts": {
        "NS2": []
      }
    },
    "NODE_0000113": {
      "aa_muts": {
        "NS2": []
      }
    },
    "NODE_0000114": {
      "aa_muts": {
        "NS2": []
      }
    },
    "NODE_0000115": {
      "aa_muts": {
        "NS2": []
      }
    },
    "NODE_0000116": {
      "aa_muts": {
        "NS2": []
      }
    },
    "NODE_0000117": {
      "aa_muts": {
        "NS2": []
      }
    },
    "NODE_0000118": {
      "aa_muts": {
        "NS2": []
      }
    },
    "NODE_0000119": {
      "aa_muts": {
        "NS2": []
      }
    },
    "NODE_0000123": {
      "aa_muts": {
        "NS2": []
      }
    },
    "NODE_0000124": {
      "aa_muts": {
        "NS2": []
      }
    },
    "NODE_0000125": {
      "aa_muts": {
        "NS2": []
      }
    },
    "NODE_0000126": {
      "aa_muts": {
        "NS2": []
      }
    },
    "NODE_0000127": {
      "aa_muts": {
        "NS2": []
      }
    },
    "NODE_0000128": {
      "aa_muts": {
        "NS2": []
      }
    },
    "NODE_0000129": {
      "aa_muts": {
        "NS2": []
      }
    },
    "NODE_0000130": {
      "aa_muts": {
        "NS2": []
      }
    },
    "NODE_0000131": {
      "aa_muts": {
        "NS2": []
      }
    },
    "NODE_0000132": {
      "aa_muts": {
        "NS2": []
      }
    },
    "NODE_0000133": {
      "aa_muts": {
        "NS2": []
      }
    },
    "NODE_0000134": {
      "aa_muts": {
        "NS2": []
      }
    },
    "NODE_0000135": {
      "aa_muts": {
        "NS2": []
      }
    },
    "NODE_0000136": {
      "aa_muts": {
        "NS2": []
      }
    },
    "NODE_0000137": {
      "aa_muts": {
        "NS2": []
      }
    },
    "NODE_0000138": {
      "aa_muts": {
        "NS2": []
      }
    },
    "NODE_0000139": {
      "aa_muts": {
        "NS2": []
      }
    },
    "NODE_0000140": {
      "aa_muts": {
        "NS2": []
      }
    },
    "NODE_0000141": {
      "aa_muts": {
        "NS2": []
      }
    },
    "NODE_0000142": {
      "aa_muts": {
        "NS2": []
      }
    },
    "NODE_0000143": {
      "aa_muts": {
        "NS2": []
      }
    },
    "NODE_0000144": {
      "aa_muts": {
        "NS2": []
      }
    },
    "NODE_0000145": {
      "aa_muts": {
        "NS2": []
      }
    },
    "NODE_0000146": {
      "aa_muts": {
        "NS2": []
      }
    },
    "NODE_0000147": {
      "aa_muts": {
        "NS2": []
      }
    },
    "NODE_0000148": {
      "aa_muts": {
        "NS2": []
      }
    },
    "NODE_0000149": {
      "aa_muts": {
        "NS2": []
      }
    },
    "NODE_0000150": {
      "aa_muts": {
        "NS2": []
      }
    },
    "NODE_0000151": {
      "aa_muts": {
        "NS2": []
      }
    },
    "NODE_0000152": {
      "aa_muts": {
        "NS2": []
      }
    },
    "NODE_0000153": {
      "aa_muts": {
        "NS2": []
      }
    },
    "NODE_0000154": {
      "aa_muts": {
        "NS2": []
      }
    },
    "NODE_0000155": {
      "aa_muts": {
        "NS2": []
      }
    },
    "NODE_0000156": {
      "aa_muts": {
        "NS2": []
      }
    },
    "NODE_0000157": {
      "aa_muts": {
        "NS2": [
          "F33L"
        ]
      }
    },
    "NODE_0000158": {
      "aa_muts": {
        "NS2": []
      }
    },
    "NODE_0000159": {
      "aa_muts": {
        "NS2": []
      }
    },
    "NODE_0000160": {
      "aa_muts": {
        "NS2": []
      }
    },
    "NODE_0000161": {
      "aa_muts": {
        "NS2": []
      }
    },
    "NODE_0000162": {
      "aa_muts": {
        "NS2": []
      }
    },
    "NODE_0000163": {
      "aa_muts": {
        "NS2": []
      }
    },
    "NODE_0000164": {
      "aa_muts": {
        "NS2": []
      }
    },
    "NODE_0000165": {
      "aa_muts": {
        "NS2": []
      }
    },
    "NODE_0000166": {
      "aa_muts": {
        "NS2": []
      }
    },
    "NODE_0000167": {
      "aa_muts": {
        "NS2": []
      }
    },
    "NODE_0000168": {
      "aa_muts": {
        "NS2": []
      }
    },
    "NODE_0000169": {
      "aa_muts": {
        "NS2": []
      }
    },
    "NODE_0000170": {
      "aa_muts": {
        "NS2": []
      }
    },
    "NODE_0000171": {
      "aa_muts": {
        "NS2": []
      }
    },
    "NODE_0000172": {
      "aa_muts": {
        "NS2": []
      }
    },
    "NODE_0000173": {
      "aa_muts": {
        "NS2": []
      }
    },
    "NODE_0000174": {
      "aa_muts": {
        "NS2": []
      }
    },
    "NODE_0000175": {
      "aa_muts": {
        "NS2": []
      }
    },
    "NODE_0000176": {
      "aa_muts": {
        "NS2": []
      }
    },
    "NODE_0000177": {
      "aa_muts": {
        "NS2": []
      }
    },
    "NODE_0000178": {
      "aa_muts": {
        "NS2": []
      }
    },
    "NODE_0000179": {
      "aa_muts": {
        "NS2": []
      }
    },
    "NODE_0000180": {
      "aa_muts": {
        "NS2": []
      }
    },
    "NODE_0000181": {
      "aa_muts": {
        "NS2": []
      }
    },
    "NODE_0000182": {
      "aa_muts": {
        "NS2": []
      }
    },
    "NODE_0000183": {
      "aa_muts": {
        "NS2": []
      }
    },
    "NODE_0000184": {
      "aa_muts": {
        "NS2": []
      }
    },
    "NODE_0000185": {
      "aa_muts": {
        "NS2": []
      }
    },
    "NODE_0000186": {
      "aa_muts": {
        "NS2": []
      }
    },
    "NODE_0000187": {
      "aa_muts": {
        "NS2": []
      }
    },
    "NODE_0000190": {
      "aa_muts": {
        "NS2": []
      }
    },
    "OK073087": {
      "aa_muts": {
        "NS2": []
      }
    },
    "OK073088": {
      "aa_muts": {
        "NS2": []
      }
    },
    "OK073089": {
      "aa_muts": {
        "NS2": []
      }
    },
    "OK073090": {
      "aa_muts": {
        "NS2": []
      }
    },
    "OK073091": {
      "aa_muts": {
        "NS2": []
      }
    },
    "OK073092": {
      "aa_muts": {
        "NS2": []
      }
    },
    "OK391221": {
      "aa_muts": {
        "NS2": []
      }
    },
    "OK391222": {
      "aa_muts": {
        "NS2": []
      }
    },
    "OK391223": {
      "aa_muts": {
        "NS2": []
      }
    },
    "OK391224": {
      "aa_muts": {
        "NS2": []
      }
    },
    "OK391225": {
      "aa_muts": {
        "NS2": []
      }
    },
    "OK391226": {
      "aa_muts": {
        "NS2": [
          "Q103L"
        ]
      }
    },
    "OK391227": {
      "aa_muts": {
        "NS2": []
      }
    },
    "OK391228": {
      "aa_muts": {
        "NS2": []
      }
    },
    "OK391229": {
      "aa_muts": {
        "NS2": []
      }
    },
    "OK391230": {
      "aa_muts": {
        "NS2": []
      }
    },
    "OK391238": {
      "aa_muts": {
        "NS2": []
      }
    },
    "OK662397": {
      "aa_muts": {
        "NS2": []
      }
    },
    "OL770287": {
      "aa_muts": {
        "NS2": []
      }
    },
    "OL770288": {
      "aa_muts": {
        "NS2": []
      }
    },
    "OL770289": {
      "aa_muts": {
        "NS2": []
      }
    },
    "OM386794": {
      "aa_muts": {
        "NS2": []
      }
    },
    "OM386795": {
      "aa_muts": {
        "NS2": []
      }
    },
    "OM386796": {
      "aa_muts": {
        "NS2": []
      }
    },
    "OM386797": {
      "aa_muts": {
        "NS2": []
      }
    },
    "OM386798": {
      "aa_muts": {
        "NS2": []
      }
    },
    "OM386799": {
      "aa_muts": {
        "NS2": []
      }
    }
  },
  "reference": {
    "NS2": "MDIWRPEKKYLRYINGFNVSELEDACFKFNYQFPKVGYCRVPSHAWCRNQGRFCATFTLYGKSKHYDKYFGVINGFTAFANTVEDAVNKLVFLAVDFITWRRQELNVYG*"
  }
}